Workbook

Sheet 需求池
A1: 需求编号 | B1: 用户需求 | C1: 适用用户 | D1: 触发情境 | E1: 期望结果 | F1: 问题编号 | G1: 证据编号 | H1: 验证优先级 | I1: 排序依据 | J1: 试验范围 | K1: 反例与边界 | L1: 研究状态
A2: N01 | B2: 准备可核对的当前上下文 | C2: 重复准备连续章节的作者 | D2: 开始新章节或场景辅助前 | E2: 快速选择本章有效资料并能删补，减少旧状态混入。 | F2: P01 P02 | G2: E017 E026 E060 E019 | H2: 优先验证 | I2: 有具体准备事件和近期回忆，适合做明确任务对照。 | J2: 核心试验 | K2: U07零背景复制；U06只有局部两句，不需要全项目初始化。 | L2: 待真实研究
A3: N02 | B3: 按章节核对人物状态 | C3: 人物关系或知情时间复杂的作者 | D3: 安排对白或继续已有情节时 | E3: 确认角色当时的关系、目的和已知信息，并跳转原文。 | F3: P02 | G3: E026 E034 E036 E064 | H3: 优先验证 | I3: U01与U03有明确过期或提前知情事件；时间边界可直接测。 | J3: 核心试验 | K3: U08人物少且正文足够；U02对自动抽取主要是担忧。 | L3: 待真实研究
A4: N03 | B4: 复核设定修改影响 | C4: 多别名多引用的复杂长篇作者 | D4: 调整规则或关键设定后 | E4: 找到可能受影响的段落逐条复核，知道哪些尚未确认。 | F4: P03 | G4: E030 E032 E062 | H4: 优先验证 | I4: 单次后果可能大，现有任务未完成覆盖确认；先测检索范围。 | J4: 独立对照试验 | K4: U05两场景改动可手工快速完成；一个案例没有全量引用真值。 | L4: 待真实研究
A5: N04 | B5: 局部采纳候选并撤销 | C5: 局部润色和分支选择作者 | D5: 比较候选或修改正文时 | E5: 只采纳认可的片段，保留原句和备选，并能撤回。 | F5: P04 | G5: E027 E061 E066 E071 | H5: 优先验证 | I5: 多种规模任务均出现选择保留行为，误覆盖的后果明确。 | J5: 核心试验 | K5: 已有流程已能选择和撤销；需求是交互约束，不能声称市场功能空白。 | L5: 待真实研究
A6: N05 | B6: 确定少量可试写的下一步 | C6: 探索型新手和局部推进作者 | D6: 不知道下一场景如何开始时 | E6: 比较少量与人物动机相关的方向，能拆分合并并先试写。 | F6: P05 P04 | G6: E023 E038 E066 E075 | H6: 优先验证 | I6: 困扰集中在取舍与场景过大，方案选择行为可以测试。 | J6: 新手对照试验 | K6: U08未使用AI且想自己练习；U02不希望长期管理大量树枝。 | L6: 待真实研究
A7: N06 | B7: 用线索找到个人素材 | C7: 跨工具保存生活片段的作者 | D7: 想复用某条旧素材时 | E7: 按关键词日期或线索定位原记录，确认是否适合当前场景。 | F7: P06 | G7: E067 E025 E042 | H7: 后续验证 | I7: 一项未完成与一项回忆支持；需要更多真实失败事件。 | J7: 素材试验后置 | K7: U05一分钟找到；U01素材不适配，检索改进未必有效。 | L7: 待真实研究
A8: N07 | B8: 保留素材原文和改写版本 | C8: 使用个人生活素材的作者 | D8: 将原素材放入故事并调整语气时 | E8: 保留当时记录的措辞和出处，候选改写独立保存。 | F8: P06 P04 | G8: E042 E069 | H8: 后续验证 | I8: 有原文保留要求和正常复用事件；作为素材试验约束。 | J8: 素材功能约束 | K8: 保留不等于必须自动改写；U05主要靠自己调整。 | L8: 待真实研究
A9: N08 | B9: 区分资料清单与实际依据 | C9: 需要核对规则或史料的作者 | D9: 检查辅助输出是否有依据时 | E9: 看见可核对来源，明确哪些只是提供过、哪些有段落关联、哪些不可确认。 | F9: P07 | G9: E028 E035 E065 E073 | H9: 优先验证 | I9: 两个不同任务均存在依据无法确认，且独立于复制负担。 | J9: 核心试验 | K9: 资料进入提示不证明模型实际使用；缺原出处时无法补足真实性。 | L9: 待真实研究
A10: N09 | B10: 以最少录入开始创作 | C10: 小规模新手和轻量辅助作者 | D10: 第一次进入或开始局部任务时 | E10: 不必先填完整世界观，能从场景或选中段落开始并逐步补充。 | F10: P10 | G10: E039 E012 E015 E074 | H10: 优先验证 | I10: 多种用户表达负担，适合比较不同初始化步骤。 | J10: 核心交互约束 | K10: U07前期维护有成本但后续顺畅；复杂长篇仍可能需完整资料。 | L10: 待真实研究
A11: N10 | B11: 在局部辅助中保留人物口吻 | C11: 希望小范围润色的作者 | D11: 改写对白或描述时 | E11: 保持人物说话习惯和作者表达，调整范围由作者指定。 | F11: P08 | G11: E024 E011 E041 E023 | H11: 后续验证 | I11: 有回忆但观察没有运行模型，需作者评价与上下文对照。 | J11: 模型质量试验 | K11: U05是历史停用；U07当前结果可接受；没有生成质量真值。 | L11: 待真实研究
A12: N11 | B12: 迁移与导出保留作品资产 | C12: 拥有既有项目的作者 | D12: 试用新工具或退出时 | E12: 保留章序正文和所承诺的备注信息，并能导出可继续写的文件。 | F12: P09 | G12: E033 E013 E045 E055 | H12: 后续验证 | I12: 影响采用，需用实际小项目验证，不能承诺所有格式。 | J12: 采用条件试验 | K12: 只有顾虑或自述，无真实导入导出任务；格式支持未定。 | L12: 待真实研究
... A17: N16 | B17: 区分个人素材与外部来源 | C17: 使用生活随笔或引用资料的作者 | D17: 把外部内容保存或用于故事时 | E17: 知道素材是个人记录还是外部摘录，保留来源与核对状态。 | F17: P07 P06 | G17: E043 E035 | H17: 基础约束 | I17: 进入素材或引用功能时需要保持来源类型；自动采集后置。 | J17: 素材功能约束 | K17: 只支持来源区分，未证明外部自动采集有价值。 | L17: 待真实研究

Sheet 方案与验证
A1: 需求编号 | B1: 用户需求 | C1: 候选实现 | D1: 较轻替代方案 | E1: 验收条件 | F1: 验证编号 | G1: 责任角色
A2: N01 | B2: 准备可核对的当前上下文 | C2: 章节目标和可编辑资料清单 | D2: 人工提示模板加原文链接 | E2: 选择第73章后只加入已确认关系；作者可移除或补充资料；保存输入清单。 | F2: V01 | G2: 产品与设计
A3: N02 | B3: 按章节核对人物状态 | C3: 手工确认的章节状态表加出处 | D3: 正文书签和时间线表 | E3: 第18章不能使用第20章才获知的信息；计划、人物说法和已确认事实分别标注。 | F3: V02 | G3: 产品与设计
A4: N03 | B4: 复核设定修改影响 | C4: 人工别名表和待复核清单 | D4: 关键词检索加章节备注 | E4: 包含已知的第19、27、41章；显示匹配理由与未复核状态；不能标成全面查完。 | F4: V03 | G4: 产品与设计
A5: N04 | B5: 局部采纳候选并撤销 | C5: 句段差异对比和确认采纳 | D5: 复制候选到独立草稿 | E5: 可只采纳一句；拒绝不改正文；撤销后与采纳前原文一致，备选仍在。 | F5: V04 | G5: 产品与设计
A6: N05 | B6: 确定少量可试写的下一步 | C6: 两至三个短方向加自由输入 | D6: 一条场景目标和人工提示 | E6: 作者可改写、组合或自写方向；保留未选方向；形成下一步动作，无需确定全书结局。 | F6: V05 | G6: 产品与设计
A7: N06 | B7: 用线索找到个人素材 | C7: 原文日期线索的统一入口 | D7: 现有备忘录标签规范 | E7: 命中结果保留原句和记录日期；未命中显示未找到；不生成内容冒充旧记录。 | F7: V06 | G7: 产品与设计
A8: N07 | B8: 保留素材原文和改写版本 | C8: 原记录只读引用加独立候选 | D8: 复制一份并附原文链接 | E8: 改写不覆盖原记录；可回到原句日期和出处；正常删改不记模型错误。 | F8: V06 | G8: 产品与设计
A9: N08 | B9: 区分资料清单与实际依据 | C9: 输入资料清单加可跳转原文 | D9: 手工引用与待查标记 | E9: 未核实来源标待查；提供给模型的资料标提供过；无实际追踪不能标为已使用依据。 | F9: V07 | G9: 产品与设计
A10: N09 | B10: 以最少录入开始创作 | C10: 正文或场景目标入口，字段可选 | D10: 按需创建表格或备注 | E10: 只给两句对白也能进入局部试验；无势力技能字段也能保存；复杂设定可后补。 | F10: V05 | G10: 产品与设计
A11: N10 | B11: 在局部辅助中保留人物口吻 | C11: 选中范围和口吻约束加对比 | D11: 只给改写建议不生成替换稿 | E11: 测试句保留明确语气约束；作者比较原句与候选；跨范围改写需重新确认。 | F11: V04 | G11: 产品与设计
A12: N11 | B12: 迁移与导出保留作品资产 | C12: 首轮仅声明并测试一种格式 | D12: 手工复制一章脱敏样本 | E12: 支持格式往返后章序正文一致；不支持项先显示并给迁移清单；无法导出不进入真实稿试点。 | F12: V08 | G12: 产品与工程
... A30: V09 | B30: 正文写作型与交互讨论型作者 | C30: 相同任务下比较固定区域、可收起区域与独立页，设备保持一致。 | D30: 正文任务完成、区域切换、误操作、注意力与偏好 | E30: 选择依任务表现与反馈，不用偏好人数确定三比二。 | F30: N15 | G30: 设计与研究

Sheet 问题归纳
A1: 问题编号 | B1: 主题 | C1: 归纳陈述 | D1: 问题性质 | E1: E或T关联人数 | F1: 仅态度人数 | G1: 反例人数 | H1: 不适用人数 | I1: 未涉及人数 | J1: 影响和时间口径 | K1: 研究判断
A2: P01 | B2: 准备有效上下文 | C2: 连续章节准备时需要挑选并重复提供背景；不同规模任务的负担不同。 | D2: 准备负担 | E2: =COUNTIFS(用户问题矩阵!C$2:C$9,"E")+COUNTIFS(用户问题矩阵!C$2:C$9,"T") -> 3 | F2: =COUNTIFS(用户问题矩阵!C$2:C$9,"A") -> 0 | G2: =COUNTIFS(用户问题矩阵!C$2:C$9,"R") -> 2 | H2: =COUNTIFS(用户问题矩阵!C$2:C$9,"N") -> 3 | I2: =COUNTIFS(用户问题矩阵!C$2:C$9,"M") -> 0 | J2: U01近期回忆11次及以上；U02为3至5次；U04为6至10次，均不是错误次数。 | K2: 优先验证整套背景负担，保留局部场景入口。
A3: P02 | B3: 确认当前章节状态 | C3: 关系、目的和知情状态缺少生效边界，旧记录可能与当前正文不同步。 | D3: 已发生阻碍 | E3: =COUNTIFS(用户问题矩阵!D$2:D$9,"E")+COUNTIFS(用户问题矩阵!D$2:D$9,"T") -> 3 | F3: =COUNTIFS(用户问题矩阵!D$2:D$9,"A") -> 1 | G3: =COUNTIFS(用户问题矩阵!D$2:D$9,"R") -> 2 | H3: =COUNTIFS(用户问题矩阵!D$2:D$9,"N") -> 0 | I3: =COUNTIFS(用户问题矩阵!D$2:D$9,"M") -> 2 | J3: 有明确事件，长期发生频率未知。 | K3: 状态要带章节与出处，保留计划和已发生的区别。
A4: P03 | B4: 复核修改影响 | C4: 改变设定后难确认哪些引用需要复核，别名与分散记录增加遗漏风险。 | D4: 已发生阻碍 | E4: =COUNTIFS(用户问题矩阵!E$2:E$9,"E")+COUNTIFS(用户问题矩阵!E$2:E$9,"T") -> 4 | F4: =COUNTIFS(用户问题矩阵!E$2:E$9,"A") -> 0 | G4: =COUNTIFS(用户问题矩阵!E$2:E$9,"R") -> 1 | H4: =COUNTIFS(用户问题矩阵!E$2:E$9,"N") -> 0 | I4: =COUNTIFS(用户问题矩阵!E$2:E$9,"M") -> 3 | J4: U02不常改主线但担心单次漏检损失；不能用高频标准直接排除。 | K4: 先比较人工别名索引和待复核清单，批量改稿后置。
A5: P04 | B5: 保留采纳与撤销控制 | C5: 作者希望选句、保留原文、保存备选，并能撤回修改。 | D5: 控制要求 | E5: =COUNTIFS(用户问题矩阵!F$2:F$9,"E")+COUNTIFS(用户问题矩阵!F$2:F$9,"T") -> 4 | F5: =COUNTIFS(用户问题矩阵!F$2:F$9,"A") -> 3 | G5: =COUNTIFS(用户问题矩阵!F$2:F$9,"R") -> 0 | H5: =COUNTIFS(用户问题矩阵!F$2:F$9,"N") -> 0 | I5: =COUNTIFS(用户问题矩阵!F$2:F$9,"M") -> 1 | J5: 多个任务已成功，证明该动作有价值，不证明现有工具都缺功能。 | K5: 作为基础交互约束，进一步测试采纳粒度与撤销。
A6: P05 | B6: 决定局部下一步 | C6: 过多或过大的方向增加选择负担，部分作者只需一个可试写的小场景。 | D6: 决策负担 | E6: =COUNTIFS(用户问题矩阵!G$2:G$9,"E")+COUNTIFS(用户问题矩阵!G$2:G$9,"T") -> 3 | F6: =COUNTIFS(用户问题矩阵!G$2:G$9,"A") -> 0 | G6: =COUNTIFS(用户问题矩阵!G$2:G$9,"R") -> 2 | H6: =COUNTIFS(用户问题矩阵!G$2:G$9,"N") -> 1 | I6: =COUNTIFS(用户问题矩阵!G$2:G$9,"M") -> 2 | J6: U04有一次约25分钟回忆；长期频率未知。 | K6: 比较少量方向与自主输入，数量上限须测试。
A7: P06 | B7: 定位并复用个人素材 | C7: 跨工具保存和缺少线索可能阻碍定位，但素材不适配与查找困难需分开。 | D7: 已发生阻碍 | E7: =COUNTIFS(用户问题矩阵!H$2:H$9,"E")+COUNTIFS(用户问题矩阵!H$2:H$9,"T") -> 2 | F7: =COUNTIFS(用户问题矩阵!H$2:H$9,"A") -> 2 | G7: =COUNTIFS(用户问题矩阵!H$2:H$9,"R") -> 2 | H7: =COUNTIFS(用户问题矩阵!H$2:H$9,"N") -> 1 | I7: =COUNTIFS(用户问题矩阵!H$2:H$9,"M") -> 1 | J7: 只有具体丢失事件可支持检索困难，7位保存者不是7位痛点用户。 | K7: 先保留原句日期和入口，再验证检索或插入辅助。
A8: P07 | B8: 检查依据与资料来源 | C8: 找到资料原文、把资料提供给模型、证明模型实际依据是不同问题。 | D8: 可核对性要求 | E8: =COUNTIFS(用户问题矩阵!I$2:I$9,"E")+COUNTIFS(用户问题矩阵!I$2:I$9,"T") -> 2 | F8: =COUNTIFS(用户问题矩阵!I$2:I$9,"A") -> 4 | G8: =COUNTIFS(用户问题矩阵!I$2:I$9,"R") -> 0 | H8: =COUNTIFS(用户问题矩阵!I$2:I$9,"N") -> 0 | I8: =COUNTIFS(用户问题矩阵!I$2:I$9,"M") -> 2 | J8: 两类任务分别为240秒与80秒的部分成功，不能认定资料或模型错误。 | K8: 提供来源和资料清单，未知的实际使用标记为不可确认。
A9: P08 | B9: 保留人物口吻与表达 | C9: 局部改写或生成可能损失人物语气，作者仍需要手工调整和选择。 | D9: 质量期望 | E9: =COUNTIFS(用户问题矩阵!J$2:J$9,"E")+COUNTIFS(用户问题矩阵!J$2:J$9,"T") -> 4 | F9: =COUNTIFS(用户问题矩阵!J$2:J$9,"A") -> 0 | G9: =COUNTIFS(用户问题矩阵!J$2:J$9,"R") -> 1 | H9: =COUNTIFS(用户问题矩阵!J$2:J$9,"N") -> 2 | I9: =COUNTIFS(用户问题矩阵!J$2:J$9,"M") -> 1 | J9: U05历史半小时和当前AI分母分开；无本次模型生成质量测试。 | K9: 限制润色范围并采用作者对照评价，暂不承诺风格一致。
A10: P09 | B10: 保留现有资产与退出能力 | C10: 新工具的价值受资料搬迁和导出能力约束，已有流程顺畅者尤其敏感。 | D10: 采用阻力 | E10: =COUNTIFS(用户问题矩阵!K$2:K$9,"E")+COUNTIFS(用户问题矩阵!K$2:K$9,"T") -> 1 | F10: =COUNTIFS(用户问题矩阵!K$2:K$9,"A") -> 3 | G10: =COUNTIFS(用户问题矩阵!K$2:K$9,"R") -> 0 | H10: =COUNTIFS(用户问题矩阵!K$2:K$9,"N") -> 0 | I10: =COUNTIFS(用户问题矩阵!K$2:K$9,"M") -> 4 | J10: 除自述外无实际迁移试验，真实转换损失未知。 | K10: 先明确支持格式，导入导出做往返核对。
A11: P10 | B11: 降低维护和界面负担 | C11: 强制录入完整设定或持续维护会打断创作，小项目更需要直接试写。 | D11: 维护负担与偏好 | E11: =COUNTIFS(用户问题矩阵!L$2:L$9,"E")+COUNTIFS(用户问题矩阵!L$2:L$9,"T") -> 2 | F11: =COUNTIFS(用户问题矩阵!L$2:L$9,"A") -> 5 | G11: =COUNTIFS(用户问题矩阵!L$2:L$9,"R") -> 1 | H11: =COUNTIFS(用户问题矩阵!L$2:L$9,"N") -> 0 | I11: =COUNTIFS(用户问题矩阵!L$2:L$9,"M") -> 0 | J11: U07前期整理一晚后流程顺畅，维护是否值得依场景变化。 | K11: 最少字段开始写，可选补充，聊天区域能收起。

Sheet 用户问题矩阵
A1: 用户 | B1: AI分组 | C1: P01 准备有效上下文 | D1: P02 确认当前章节状态 | E1: P03 复核修改影响 | F1: P04 保留采纳与撤销控制 | G1: P05 决定局部下一步 | H1: P06 定位并复用个人素材 | I1: P07 检查依据与资料来源 | J1: P08 保留人物口吻与表达 | K1: P09 保留现有资产与退出能力 | L1: P10 降低维护和界面负担
A2: U01 | B2: 高频AI | C2: E | D2: E | E2: T | F2: E | G2: E | H2: R | I2: A | J2: T | K2: A | L2: A
A3: U02 | B3: 低频AI | C3: T | D3: A | E3: E | F3: A | G3: R | H3: A | I3: A | J3: M | K3: A | L3: A
A4: U03 | B4: 未使用AI | C4: N | D4: E | E4: E | F4: A | G4: M | H4: M | I4: E | J4: N | K4: M | L4: A
A5: U04 | B5: 高频AI | C5: T | D5: T | E5: T | F5: E | G5: E | H5: E | I5: A | J5: T | K5: M | L5: A
A6: U05 | B6: 已停用AI | C6: N | D6: R | E6: R | F6: A | G6: R | H6: R | I6: A | J6: T | K6: A | L6: T
A7: U06 | B7: 低频AI | C7: R | D7: M | E7: M | F7: E | G7: N | H7: A | I7: M | J7: T | K7: M | L7: A
A8: U07 | B8: 高频AI | C8: R | D8: M | E8: M | F8: M | G8: M | H8: T | I8: E | J8: R | K8: T | L8: R
A9: U08 | B9: 未使用AI | C9: N | D9: R | E9: M | F9: E | G9: E | H9: N | I9: M | J9: N | K9: M | L9: E
A12: E含正常完成事件，不等于未满足痛点；同用户按问题只计一次。
A13: U05在P08的T为历史经历；P01的N不进入当前AI背景准备统计。

Sheet 任务统计
A1: 任务编号 | B1: 用户 | C1: 原记录结果 | D1: 秒 | E1: 切换次 | F1: 查找次 | G1: 搬运次 | H1: 错误项 | I1: 任务目标 | J1: 原完成条件 | K1: 原结果说明
A2: OBS-U01-T1 | B2: U01 | C2: 成功 | D2: =IF(COUNTIFS(任务步骤!B$2:B$48,A2,任务步骤!F$2:F$48,"待补时间")>0,"待补时间",SUMIFS(任务步骤!F$2:F$48,任务步骤!B$2:B$48,A2)) -> 269 | E2: =SUMIFS(任务步骤!I$2:I$48,任务步骤!B$2:B$48,A2) -> 3 | F2: =SUMIFS(任务步骤!J$2:J$48,任务步骤!B$2:B$48,A2) -> 3 | G2: =SUMIFS(任务步骤!K$2:K$48,任务步骤!B$2:B$48,A2) -> 3 | H2: =SUMIFS(任务步骤!L$2:L$48,任务步骤!B$2:B$48,A2) -> 1 | I2: 准备第73章AI候选场景所需的当前人物关系与前文 | J2: 找到最新关系和前文摘要，放入草稿提示，不提交原稿 | K2: 提示准备完成；未运行模型。错误为旧表未更新，不是本次AI输出。
A3: OBS-U01-T2 | B3: U01 | C3: 成功 | D3: =IF(COUNTIFS(任务步骤!B$2:B$48,A3,任务步骤!F$2:F$48,"待补时间")>0,"待补时间",SUMIFS(任务步骤!F$2:F$48,任务步骤!B$2:B$48,A3)) -> 150 | E3: =SUMIFS(任务步骤!I$2:I$48,任务步骤!B$2:B$48,A3) -> 0 | F3: =SUMIFS(任务步骤!J$2:J$48,任务步骤!B$2:B$48,A3) -> 2 | G3: =SUMIFS(任务步骤!K$2:K$48,任务步骤!B$2:B$48,A3) -> 0 | H3: =SUMIFS(任务步骤!L$2:L$48,任务步骤!B$2:B$48,A3) -> 0 | I3: 比较第73章两个剧情方向并保存选中的候选 | J3: 说明采用理由，保留另一方案，候选不覆盖正文 | K3: 选择完成；没有为了增加分支而请求更多方案。
A4: OBS-U02-T1 | B4: U02 | C4: 部分成功 | D4: =IF(COUNTIFS(任务步骤!B$2:B$48,A4,任务步骤!F$2:F$48,"待补时间")>0,"待补时间",SUMIFS(任务步骤!F$2:F$48,任务步骤!B$2:B$48,A4)) -> 300 | E4: =SUMIFS(任务步骤!I$2:I$48,任务步骤!B$2:B$48,A4) -> 0 | F4: =SUMIFS(任务步骤!J$2:J$48,任务步骤!B$2:B$48,A4) -> 4 | G4: =SUMIFS(任务步骤!K$2:K$48,任务步骤!B$2:B$48,A4) -> 0 | H4: =SUMIFS(任务步骤!L$2:L$48,任务步骤!B$2:B$48,A4) -> 0 | I4: 修改通行规则后找到可能受影响的旧章节 | J4: 找到两处已知引用并检查道具别名；不自动改稿 | K4: 300秒停止，找到3处但无法确认是否完整；未完成覆盖复核。
A5: OBS-U02-T2 | B5: U02 | C5: 成功 | D5: =IF(COUNTIFS(任务步骤!B$2:B$48,A5,任务步骤!F$2:F$48,"待补时间")>0,"待补时间",SUMIFS(任务步骤!F$2:F$48,任务步骤!B$2:B$48,A5)) -> 180 | E5: =SUMIFS(任务步骤!I$2:I$48,任务步骤!B$2:B$48,A5) -> 0 | F5: =SUMIFS(任务步骤!J$2:J$48,任务步骤!B$2:B$48,A5) -> 3 | G5: =SUMIFS(任务步骤!K$2:K$48,任务步骤!B$2:B$48,A5) -> 0 | H5: =SUMIFS(任务步骤!L$2:L$48,任务步骤!B$2:B$48,A5) -> 0 | I5: 找到第12章埋下的铜扣伏笔及计划回收位置 | J5: 找到埋设、关联角色和待回收章纲 | K5: 埋设与计划回收位置已明确；没有把待回收写成已发生。
A6: OBS-U03-T1 | B6: U03 | C6: 成功 | D6: =IF(COUNTIFS(任务步骤!B$2:B$48,A6,任务步骤!F$2:F$48,"待补时间")>0,"待补时间",SUMIFS(任务步骤!F$2:F$48,任务步骤!B$2:B$48,A6)) -> 195 | E6: =SUMIFS(任务步骤!I$2:I$48,任务步骤!B$2:B$48,A6) -> 2 | F6: =SUMIFS(任务步骤!J$2:J$48,任务步骤!B$2:B$48,A6) -> 3 | G6: =SUMIFS(任务步骤!K$2:K$48,任务步骤!B$2:B$48,A6) -> 0 | H6: =SUMIFS(任务步骤!L$2:L$48,任务步骤!B$2:B$48,A6) -> 1 | I6: 确认人物在第18章是否已经知道账册被替换 | J6: 找出此前知情记录和原文，说明消息来源 | K6: 195秒内发现并修正时间状态错误；错误来自手工维护。
A7: OBS-U03-T2 | B7: U03 | C7: 部分成功 | D7: =IF(COUNTIFS(任务步骤!B$2:B$48,A7,任务步骤!F$2:F$48,"待补时间")>0,"待补时间",SUMIFS(任务步骤!F$2:F$48,任务步骤!B$2:B$48,A7)) -> 240 | E7: =SUMIFS(任务步骤!I$2:I$48,任务步骤!B$2:B$48,A7) -> 2 | F7: =SUMIFS(任务步骤!J$2:J$48,任务步骤!B$2:B$48,A7) -> 3 | G7: =SUMIFS(任务步骤!K$2:K$48,任务步骤!B$2:B$48,A7) -> 0 | H7: =SUMIFS(任务步骤!L$2:L$48,任务步骤!B$2:B$48,A7) -> 0 | I7: 找到人物行程是否与集市开市时间冲突的资料依据 | J7: 找到行程记录及可核对的历史来源 | K7: 240秒停止；确认故事时间，但无法核对史料来源，记部分成功。
A8: OBS-U04-T1 | B8: U04 | C8: 成功 | D8: =IF(COUNTIFS(任务步骤!B$2:B$48,A8,任务步骤!F$2:F$48,"待补时间")>0,"待补时间",SUMIFS(任务步骤!F$2:F$48,任务步骤!B$2:B$48,A8)) -> 180 | E8: =SUMIFS(任务步骤!I$2:I$48,任务步骤!B$2:B$48,A8) -> 1 | F8: =SUMIFS(任务步骤!J$2:J$48,任务步骤!B$2:B$48,A8) -> 2 | G8: =SUMIFS(任务步骤!K$2:K$48,任务步骤!B$2:B$48,A8) -> 1 | H8: =SUMIFS(任务步骤!L$2:L$48,任务步骤!B$2:B$48,A8) -> 0 | I8: 从现有三条剧情方向中选第5章开场并保留备选 | J8: 选一方向写出场景目标，保留其余方案，不要求完成正文 | K8: 180秒完成方案取舍；选中的目标为用户重新组合。
A9: OBS-U04-T2 | B9: U04 | C9: 未完成 | D9: =IF(COUNTIFS(任务步骤!B$2:B$48,A9,任务步骤!F$2:F$48,"待补时间")>0,"待补时间",SUMIFS(任务步骤!F$2:F$48,任务步骤!B$2:B$48,A9)) -> 300 | E9: =SUMIFS(任务步骤!I$2:I$48,任务步骤!B$2:B$48,A9) -> 2 | F9: =SUMIFS(任务步骤!J$2:J$48,任务步骤!B$2:B$48,A9) -> 4 | G9: =SUMIFS(任务步骤!K$2:K$48,任务步骤!B$2:B$48,A9) -> 0 | H9: =SUMIFS(任务步骤!L$2:L$48,任务步骤!B$2:B$48,A9) -> 0 | I9: 找到一条与第5章车站场景相关的生活素材 | J9: 定位可用的旧素材，并说明如何进入当前场景 | K9: 300秒未找到预期素材；没有用新生成内容冒充旧素材。
A10: OBS-U05-T1 | B10: U05 | C10: 成功 | D10: =IF(COUNTIFS(任务步骤!B$2:B$48,A10,任务步骤!F$2:F$48,"待补时间")>0,"待补时间",SUMIFS(任务步骤!F$2:F$48,任务步骤!B$2:B$48,A10)) -> 60 | E10: =SUMIFS(任务步骤!I$2:I$48,任务步骤!B$2:B$48,A10) -> 0 | F10: =SUMIFS(任务步骤!J$2:J$48,任务步骤!B$2:B$48,A10) -> 1 | G10: =SUMIFS(任务步骤!K$2:K$48,任务步骤!B$2:B$48,A10) -> 0 | H10: =SUMIFS(任务步骤!L$2:L$48,任务步骤!B$2:B$48,A10) -> 0 | I10: 找到上周记录的雨夜等车片段 | J10: 找到原文与日期，保留当时的措辞 | K10: 60秒完成；没有明显检索困难，是素材管理需求的反例。
A11: OBS-U05-T2 | B11: U05 | C11: 成功 | D11: =IF(COUNTIFS(任务步骤!B$2:B$48,A11,任务步骤!F$2:F$48,"待补时间")>0,"待补时间",SUMIFS(任务步骤!F$2:F$48,任务步骤!B$2:B$48,A11)) -> 120 | E11: =SUMIFS(任务步骤!I$2:I$48,任务步骤!B$2:B$48,A11) -> 1 | F11: =SUMIFS(任务步骤!J$2:J$48,任务步骤!B$2:B$48,A11) -> 0 | G11: =SUMIFS(任务步骤!K$2:K$48,任务步骤!B$2:B$48,A11) -> 1 | H11: =SUMIFS(任务步骤!L$2:L$48,任务步骤!B$2:B$48,A11) -> 0 | I11: 把该素材放入第7章候选稿并保留原记录 | J11: 使用局部素材，原文不被覆盖，作者完成语气调整 | K11: 120秒完成局部使用；删改属正常创作，不记AI纠错或返工。
A12: OBS-U06-T1 | B12: U06 | C12: 成功 | D12: =IF(COUNTIFS(任务步骤!B$2:B$48,A12,任务步骤!F$2:F$48,"待补时间")>0,"待补时间",SUMIFS(任务步骤!F$2:F$48,任务步骤!B$2:B$48,A12)) -> 100 | E12: =SUMIFS(任务步骤!I$2:I$48,任务步骤!B$2:B$48,A12) -> 1 | F12: =SUMIFS(任务步骤!J$2:J$48,任务步骤!B$2:B$48,A12) -> 1 | G12: =SUMIFS(任务步骤!K$2:K$48,任务步骤!B$2:B$48,A12) -> 1 | H12: =SUMIFS(任务步骤!L$2:L$48,任务步骤!B$2:B$48,A12) -> 0 | I12: 给一小段告别对白准备局部润色指令 | J12: 指定人物口吻与局部范围，不要求补全章设定 | K12: 100秒完成；仅1次局部文本搬运，未运行本次模型。
A13: OBS-U06-T2 | B13: U06 | C13: 成功 | D13: =IF(COUNTIFS(任务步骤!B$2:B$48,A13,任务步骤!F$2:F$48,"待补时间")>0,"待补时间",SUMIFS(任务步骤!F$2:F$48,任务步骤!B$2:B$48,A13)) -> 130 | E13: =SUMIFS(任务步骤!I$2:I$48,任务步骤!B$2:B$48,A13) -> 0 | F13: =SUMIFS(任务步骤!J$2:J$48,任务步骤!B$2:B$48,A13) -> 1 | G13: =SUMIFS(任务步骤!K$2:K$48,任务步骤!B$2:B$48,A13) -> 0 | H13: =SUMIFS(任务步骤!L$2:L$48,任务步骤!B$2:B$48,A13) -> 0 | I13: 选择旧润色结果的一小段并撤回另一句修改 | J13: 只采纳认可的句子，能够回到原句 | K13: 130秒完成；以已有候选演示选择和撤销，不宣称验证模型效果。
... A17: OBS-U08-T2 | B17: U08 | C17: 成功 | D17: =IF(COUNTIFS(任务步骤!B$2:B$48,A17,任务步骤!F$2:F$48,"待补时间")>0,"待补时间",SUMIFS(任务步骤!F$2:F$48,任务步骤!B$2:B$48,A17)) -> 110 | E17: =SUMIFS(任务步骤!I$2:I$48,任务步骤!B$2:B$48,A17) -> 1 | F17: =SUMIFS(任务步骤!J$2:J$48,任务步骤!B$2:B$48,A17) -> 1 | G17: =SUMIFS(任务步骤!K$2:K$48,任务步骤!B$2:B$48,A17) -> 0 | H17: =SUMIFS(任务步骤!L$2:L$48,任务步骤!B$2:B$48,A17) -> 0 | I17: 从两条自行写的后续方向中确定一次试写 | J17: 明确一个小场景动作；不要求确定全书结局 | K17: 110秒完成局部推进；未测试AI生成和长期规划。

Sheet 任务步骤
A1: 步骤编号 | B1: 任务编号 | C1: 用户 | D1: 起点秒 | E1: 终点秒 | F1: 时长秒 | G1: 原记录操作摘要 | H1: 工具 | I1: 切换次 | J1: 查找次 | K1: 搬运次 | L1: 错误项
A2: OBS-U01-T1-E01 | B2: OBS-U01-T1 | C2: U01 | D2: 0 | E2: 35 | F2: =IF(AND(ISNUMBER(D2),ISNUMBER(E2)),E2-D2,"待补时间") -> 35 | G2: 打开章纲，确认第73章冲突目标 | H2: Word | I2: 0 | J2: 1 | K2: 0 | L2: 0
A3: OBS-U01-T1-E02 | B3: OBS-U01-T1 | C3: U01 | D3: 35 | E3: 113 | F3: =IF(AND(ISNUMBER(D3),ISNUMBER(E3)),E3-D3,"待补时间") -> 78 | G3: 切到关系表发现记录仍停在第69章 | H3: Excel | I3: 1 | J3: 1 | K3: 0 | L3: 1
A4: OBS-U01-T1-E03 | B4: OBS-U01-T1 | C4: U01 | D4: 113 | E4: 217 | F4: =IF(AND(ISNUMBER(D4),ISNUMBER(E4)),E4-D4,"待补时间") -> 104 | G4: 返回第71章找到决裂段落，复制摘要与章纲 | H4: Word | I4: 1 | J4: 1 | K4: 2 | L4: 0
A5: OBS-U01-T1-E04 | B5: OBS-U01-T1 | C5: U01 | D5: 217 | E5: 269 | F5: =IF(AND(ISNUMBER(D5),ISNUMBER(E5)),E5-D5,"待补时间") -> 52 | G5: 切到AI草稿框并补入最新关系，标明禁止和解 | H5: DeepSeek | I5: 1 | J5: 0 | K5: 1 | L5: 0
A6: OBS-U01-T2-E01 | B6: OBS-U01-T2 | C6: U01 | D6: 0 | E6: 42 | F6: =IF(AND(ISNUMBER(D6),ISNUMBER(E6)),E6-D6,"待补时间") -> 42 | G6: 查看自己先前保存的两个草稿方向 | H6: Word | I6: 0 | J6: 1 | K6: 0 | L6: 0
A7: OBS-U01-T2-E02 | B7: OBS-U01-T2 | C7: U01 | D7: 42 | E7: 110 | F7: =IF(AND(ISNUMBER(D7),ISNUMBER(E7)),E7-D7,"待补时间") -> 68 | G7: 核对是否违反第71章的决裂状态 | H7: Word | I7: 0 | J7: 1 | K7: 0 | L7: 0
A8: OBS-U01-T2-E03 | B8: OBS-U01-T2 | C8: U01 | D8: 110 | E8: 150 | F8: =IF(AND(ISNUMBER(D8),ISNUMBER(E8)),E8-D8,"待补时间") -> 40 | G8: 选对峙而非合作，将另一方案移入备选区 | H8: Word | I8: 0 | J8: 0 | K8: 0 | L8: 0
A9: OBS-U02-T1-E01 | B9: OBS-U02-T1 | C9: U02 | D9: 0 | E9: 55 | F9: =IF(AND(ISNUMBER(D9),ISNUMBER(E9)),E9-D9,"待补时间") -> 55 | G9: 用正式道具名搜索，定位第19章 | H9: Scrivener | I9: 0 | J9: 1 | K9: 0 | L9: 0
A10: OBS-U02-T1-E02 | B10: OBS-U02-T1 | C10: U02 | D10: 55 | E10: 141 | F10: =IF(AND(ISNUMBER(D10),ISNUMBER(E10)),E10-D10,"待补时间") -> 86 | G10: 修改第19章备注，搜索第41章渡河段落 | H10: Scrivener | I10: 0 | J10: 1 | K10: 0 | L10: 0
A11: OBS-U02-T1-E03 | B11: OBS-U02-T1 | C11: U02 | D11: 141 | E11: 243 | F11: =IF(AND(ISNUMBER(D11),ISNUMBER(E11)),E11-D11,"待补时间") -> 102 | G11: 想到另一个称呼，回设定页查别名 | H11: Scrivener | I11: 0 | J11: 1 | K11: 0 | L11: 0
A12: OBS-U02-T1-E04 | B12: OBS-U02-T1 | C12: U02 | D12: 243 | E12: 300 | F12: =IF(AND(ISNUMBER(D12),ISNUMBER(E12)),E12-D12,"待补时间") -> 57 | G12: 用别名定位第27章；仍不确定有无其他称呼 | H12: Scrivener | I12: 0 | J12: 1 | K12: 0 | L12: 0
A13: OBS-U02-T2-E01 | B13: OBS-U02-T2 | C13: U02 | D13: 0 | E13: 44 | F13: =IF(AND(ISNUMBER(D13),ISNUMBER(E13)),E13-D13,"待补时间") -> 44 | G13: 在便签里找到伏笔名与第12章记录 | H13: Scrivener | I13: 0 | J13: 1 | K13: 0 | L13: 0
... A48: OBS-U08-T2-E03 | B48: OBS-U08-T2 | C48: U08 | D48: 80 | E48: 110 | F48: =IF(AND(ISNUMBER(D48),ISNUMBER(E48)),E48-D48,"待补时间") -> 30 | G48: 保留另一个想法，没有删除 | H48: Word | I48: 0 | J48: 0 | K48: 0 | L48: 0

Sheet 证据编码
A1: 证据编号 | B1: 用户 | C1: 来源定位 | D1: 原文页 | E1: 资料类型 | F1: 时间口径 | G1: 来源摘要 | H1: 问题编号 | I1: 作用 | J1: 分析解释
A2: E001 | B2: U01 | C2: BQ-U01-Q16 | D2: 6 | E2: 偏好 | F2: 未指定频率 | G2: 让本次生成使用人物在这一章的状态，而不是最初的人设。 | H2: P01 P02 | I2: 支持 | J2: 改善愿望用于明确目标；仍需具体事件与试验支持。
A3: E002 | B3: U01 | C3: BQ-U01-Q17 | D3: 6 | E3: 取舍态度 | F3: 未指定频率 | G3: 先减少每次生成前重复整理上下文；关系图可以之后再说。 | H3: P01 P02 | I3: 支持 | J3: 同一用户的第二条态度不另算一位用户。
A4: E003 | B4: U02 | C4: BQ-U02-Q16 | D4: 7 | E4: 偏好 | F4: 未指定频率 | G4: 知道改动可能影响哪些段落，并能逐条复核。 | H4: P03 | I4: 支持 | J4: 改善愿望用于明确目标；仍需具体事件与试验支持。
A5: E004 | B5: U02 | C5: BQ-U02-Q17 | D5: 7 | E5: 取舍态度 | F5: 未指定频率 | G5: 先定位修改影响；不希望系统自动改完几十章。 | H5: P03 | I5: 支持 | J5: 同一用户的第二条态度不另算一位用户。
A6: E005 | B6: U03 | C6: BQ-U03-Q16 | D6: 8 | E6: 偏好 | F6: 未指定频率 | G6: 按章节确认角色当时知道什么，并找到原文依据。 | H6: P02 P07 | I6: 支持 | J6: 改善愿望用于明确目标；仍需具体事件与试验支持。
A7: E006 | B7: U03 | C7: BQ-U03-Q17 | D7: 8 | E7: 取舍态度 | F7: 未指定频率 | G7: 优先核对人物知情状态；人物名字和年龄通常不难找。 | H7: P02 P07 | I7: 支持 | J7: 同一用户的第二条态度不另算一位用户。
A8: E007 | B8: U04 | C8: BQ-U04-Q16 | D8: 9 | E8: 偏好 | F8: 未指定频率 | G8: 少量方案要说明与当前人物动机的关系，能先留作备选。 | H8: P05 | I8: 支持 | J8: 改善愿望用于明确目标；仍需具体事件与试验支持。
A9: E008 | B9: U04 | C9: BQ-U04-Q17 | D9: 9 | E9: 取舍态度 | F9: 未指定频率 | G9: 先让我能选下一步；完整卷纲会让我更难开始。 | H9: P05 | I9: 支持 | J9: 同一用户的第二条态度不另算一位用户。
A10: E009 | B10: U05 | C10: BQ-U05-Q16 | D10: 10 | E10: 偏好 | F10: 未指定频率 | G10: 快速找到自己的生活片段，保留原来的语气与出处。 | H10: P06 P10 | I10: 支持 | J10: 改善愿望用于明确目标；仍需具体事件与试验支持。
A11: E010 | B11: U05 | C11: BQ-U05-Q17 | D11: 10 | E11: 取舍态度 | F11: 未指定频率 | G11: 先把素材保存和找到做好；不希望为AI维护很多字段。 | H11: P06 P10 | I11: 支持 | J11: 同一用户的第二条态度不另算一位用户。
A12: E011 | B12: U06 | C12: BQ-U06-Q16 | D12: 11 | E12: 偏好 | F12: 未指定频率 | G12: 局部润色时保留人物口吻并能只采纳一小段。 | H12: P04 P08 | I12: 支持 | J12: 改善愿望用于明确目标；仍需具体事件与试验支持。
A13: E012 | B13: U06 | C13: BQ-U06-Q17 | D13: 11 | E13: 取舍态度 | F13: 未指定频率 | G13: 先做方便的局部修改；不想为每章重新建一套资料。 | H13: P04 P08 | I13: 支持 | J13: 同一用户的第二条态度不另算一位用户。
... A76: E075 | B76: U08 | C76: OBS-U08-T2 | D76: 31 | E76: 模拟任务结果 | F76: 任务内相对时间 | G76: 成功，110秒。110秒完成局部推进；未测试AI生成和长期规划。 | H76: P04 P05 | I76: 支持 | J76: 短任务推进可能比完整大纲更适合当前阶段

Sheet 样本与口径
A1: 用户 | B1: 创作类型 | C1: 字数 | D1: 主要人物数 | E1: 创作方式 | F1: AI分组 | G1: 当前工具 | H1: 资料范围
A2: U01 | B2: 悬疑连载 | C2: 240000 | D2: 12 | E2: 混合型 | F2: 高频AI | G2: Word、DeepSeek、Excel | H2: 问卷 访谈 任务
A3: U02 | B3: 幻想长篇 | C3: 480000 | D3: 28 | E3: 先规划型 | F3: 低频AI | G3: Scrivener、Claude、手机备忘录 | H3: 问卷 访谈 任务
A4: U03 | B4: 历史题材故事 | C4: 72000 | D4: 9 | E4: 先规划型 | F4: 未使用AI | G4: Word、Excel、纸质摘记 | H4: 问卷 访谈 任务
A5: U04 | B5: 科幻新人长篇 | C5: 12000 | D5: 4 | E5: 边写边发现型 | F5: 高频AI | G5: Obsidian、豆包、手机备忘录 | H5: 问卷 访谈 任务
A6: U05 | B6: 现实题材故事 | C6: 35000 | D6: 5 | E6: 边写边发现型 | F6: 已停用AI | G6: Word、手机备忘录 | H6: 问卷 访谈 任务
A7: U06 | B7: 都市言情连载 | C7: 185000 | D7: 8 | E7: 混合型 | F7: 低频AI | G7: 作家助手、豆包、手机备忘录 | H7: 问卷 任务，无访谈
A8: U07 | B8: 科幻长篇 | C8: 96000 | D8: 7 | E8: 先规划型 | F8: 高频AI | G8: Notion、ChatGPT | H8: 问卷 任务，无访谈
A9: U08 | B9: 儿童幻想长篇起稿 | C9: 6200 | D9: 3 | E9: 混合型 | F9: 未使用AI | G9: Word、手机备忘录 | H9: 问卷 任务，无访谈
A12: 口径编号 | B12: 需处理的问题 | C12: 来源范围 | D12: 分析处理 | E12: 结果解释
A13: D01 | B13: 样本为教学模拟 | C13: 全部 | D13: 保持教学性质，所有推断待真实研究 | E13: 不做市场比例、显著性或投资收益推断。
A14: D02 | B14: U05时间口径不一致 | C14: BQ-U05-Q6 与 IV-U05-Q7 | D14: 按完整访谈暂归五个月前历史经历 | E14: 不纳入近期AI质量统计，真实研究须回访确认。
A15: D03 | B15: AI跳题不是零次 | C15: U03 U05 U08 的 Q8 Q11 | D15: 不适用保持文字标记 | E15: U07的0次为适用后的答案，保留为反例。
A16: D04 | B16: 用户及任务不可重复加总 | C16: 同用户BQ IV OBS | D16: 问题关联计数按用户去重 | E16: 同一事件可编码多问题，问题计数不能相加为用户总数。
A17: D05 | B17: 任务异质且无产品对照 | C17: 16项OBS | D17: 秒数只描述本项任务 | E17: 12项成功不作为新产品成功率，不能平均后宣称提效。
A18: D06 | B18: 来源缺失不自动算错误 | C18: OBS-U03-T2 OBS-U07-T2 | D18: 保留部分成功和原始错误0 | E18: 未知真伪及未知采用与已发现错误分开。
A19: D07 | B19: 当前付费不等于为本产品付费 | C19: BQ-Q15 | D19: 仅说明已有支出 | E19: 无价格接受度和订阅意愿测试。
A20: D08 | B20: 无工程成本与自动化质量数据 | C20: 技术设想 | D20: 只排序验证，不用虚构RICE投入 | E20: 进入排期前补工程估算和同任务基线。
A23: 步骤 | B23: 操作 | C23: 输出 | G23: 需求验证分组 | H23: 数量
A24: 1 | B24: 统一用户编号时间分支与任务计数 | C24: 样本与口径 任务步骤 | G24: 优先验证 | H24: =COUNTIFS(需求池!H2:H17,G24) -> 7
A25: 2 | B25: 拆记录为摘要，保留来源与解释 | C25: 证据编码 | G25: 后续验证 | H25: =COUNTIFS(需求池!H2:H17,G25) -> 6
A26: 3 | B26: 按情境合并主题，并记录反例 | C26: 问题归纳 用户问题矩阵 | G26: 基础约束 | H26: =COUNTIFS(需求池!H2:H17,G26) -> 3
A27: 4 | B27: 写触发情境与期望结果，拆开方案 | C27: 需求池
A28: 5 | B28: 按事件影响边界安排验证顺序 | C28: 需求池验证优先级 | G28: 黄色研究状态可编辑；优先级和状态有下拉选项。
A29: 6 | B29: 比较方案，定验收与继续条件 | C29: 方案与验证 | G29: 修改步骤或矩阵后，汇总计数重算。报告正文为本次版本快照。
